nr_all/__init__.py
nr_all/config.py
nr_all/constants.py
nr_all/ext.py
nr_all/fetchers.py
nr_all/minters.py
nr_all/record.py
nr_all/search.py
nr_all/serializers.py
nr_all/translations/cs/LC_MESSAGES/messages.po
nr_all/translations/en/LC_MESSAGES/messages.po
techlib_nr_all-1.0.0a16.dist-info/entry_points.txt
techlib_nr_all-1.0.0a16.dist-info/LICENSE
techlib_nr_all-1.0.0a16.dist-info/WHEEL
techlib_nr_all-1.0.0a16.dist-info/METADATA
techlib_nr_all-1.0.0a16.dist-info/RECORD
